[{"pk": 13, "model": "contenttypes.contenttype", "fields": {"model": "background_video", "name": "Background Video", "app_label": "story_database"}}, {"pk": 11, "model": "contenttypes.contenttype", "fields": {"model": "category", "name": "Category", "app_label": "story_database"}}, {"pk": 30, "model": "contenttypes.contenttype", "fields": {"model": "featured_story", "name": "Featured Story", "app_label": "story_database"}}, {"pk": 22, "model": "contenttypes.contenttype", "fields": {"model": "infographic", "name": "Infographic", "app_label": "story_database"}}, {"pk": 20, "model": "contenttypes.contenttype", "fields": {"model": "photo_gallery", "name": "Photo Gallery", "app_label": "story_database"}}, {"pk": 17, "model": "contenttypes.contenttype", "fields": {"model": "poster_frame", "name": "Poster Frame", "app_label": "story_database"}}, {"pk": 24, "model": "contenttypes.contenttype", "fields": {"model": "related_content", "name": "Related Content", "app_label": "story_database"}}, {"pk": 10, "model": "contenttypes.contenttype", "fields": {"model": "resources", "name": "Resource", "app_label": "story_database"}}, {"pk": 31, "model": "contenttypes.contenttype", "fields": {"model": "about_page", "name": "about_ page", "app_label": "story_database"}}, {"pk": 32, "model": "contenttypes.contenttype", "fields": {"model": "about_page_translation", "name": "about_ page_ translation", "app_label": "story_database"}}, {"pk": 12, "model": "contenttypes.contenttype", "fields": {"model": "category_translation", "name": "category_ translation", "app_label": "story_database"}}, {"pk": 5, "model": "contenttypes.contenttype", "fields": {"model": "contenttype", "name": "content type", "app_label": "contenttypes"}}, {"pk": 2, "model": "contenttypes.contenttype", "fields": {"model": "group", "name": "group", "app_label": "auth"}}, {"pk": 23, "model": "contenttypes.contenttype", "fields": {"model": "infographic_translation", "name": "infographic_ translation", "app_label": "story_database"}}, {"pk": 8, "model": "contenttypes.contenttype", "fields": {"model": "logentry", "name": "log entry", "app_label": "admin"}}, {"pk": 4, "model": "contenttypes.contenttype", "fields": {"model": "message", "name": "message", "app_label": "auth"}}, {"pk": 1, "model": "contenttypes.contenttype", "fields": {"model": "permission", "name": "permission", "app_label": "auth"}}, {"pk": 18, "model": "contenttypes.contenttype", "fields": {"model": "photo", "name": "photo", "app_label": "story_database"}}, {"pk": 21, "model": "contenttypes.contenttype", "fields": {"model": "photo_gallery_translation", "name": "photo_ gallery_ translation", "app_label": "story_database"}}, {"pk": 19, "model": "contenttypes.contenttype", "fields": {"model": "photo_translation", "name": "photo_ translation", "app_label": "story_database"}}, {"pk": 25, "model": "contenttypes.contenttype", "fields": {"model": "related_content_translation", "name": "related_ content_ translation", "app_label": "story_database"}}, {"pk": 28, "model": "contenttypes.contenttype", "fields": {"model": "research", "name": "research", "app_label": "story_database"}}, {"pk": 29, "model": "contenttypes.contenttype", "fields": {"model": "research_translation", "name": "research_ translation", "app_label": "story_database"}}, {"pk": 6, "model": "contenttypes.contenttype", "fields": {"model": "session", "name": "session", "app_label": "sessions"}}, {"pk": 7, "model": "contenttypes.contenttype", "fields": {"model": "site", "name": "site", "app_label": "sites"}}, {"pk": 9, "model": "contenttypes.contenttype", "fields": {"model": "site", "name": "site", "app_label": "story_database"}}, {"pk": 26, "model": "contenttypes.contenttype", "fields": {"model": "story", "name": "story", "app_label": "story_database"}}, {"pk": 27, "model": "contenttypes.contenttype", "fields": {"model": "story_translation", "name": "story_ translation", "app_label": "story_database"}}, {"pk": 14, "model": "contenttypes.contenttype", "fields": {"model": "tag", "name": "tag", "app_label": "story_database"}}, {"pk": 15, "model": "contenttypes.contenttype", "fields": {"model": "tag_translation", "name": "tag_ translation", "app_label": "story_database"}}, {"pk": 3, "model": "contenttypes.contenttype", "fields": {"model": "user", "name": "user", "app_label": "auth"}}, {"pk": 16, "model": "contenttypes.contenttype", "fields": {"model": "video", "name": "video", "app_label": "story_database"}}, {"pk": "2738287899c262ca53859db8279801d9", "model": "sessions.session", "fields": {"expire_date": "2012-04-17 23:07:34", "session_data": "ZWYxYWI4ZDdjYzg2NjRhNWE2ZjQzMzA2NWM2ZTNlZmMxZGI4NzNmNDqAAn1xAShVEl9hdXRoX3Vz\nZXJfYmFja2VuZHECVSlkamFuZ28uY29udHJpYi5hdXRoLmJhY2tlbmRzLk1vZGVsQmFja2VuZHED\nVQ1fYXV0aF91c2VyX2lkcQRLAXUu\n"}}, {"pk": 1, "model": "sites.site", "fields": {"domain": "example.com", "name": "example.com"}}, {"pk": 16, "model": "admin.logentry", "fields": {"action_flag": 1, "action_time": "2012-04-17 22:27:58", "object_repr": "Story Two", "object_id": "2", "change_message": "", "user": 1, "content_type": 26}}, {"pk": 15, "model": "admin.logentry", "fields": {"action_flag": 2, "action_time": "2012-04-17 06:40:36", "object_repr": "Story One", "object_id": "1", "change_message": "Changed category.", "user": 1, "content_type": 26}}, {"pk": 14, "model": "admin.logentry", "fields": {"action_flag": 2, "action_time": "2012-04-17 06:40:14", "object_repr": "background video 1", "object_id": "1", "change_message": "Changed category.", "user": 1, "content_type": 13}}, {"pk": 13, "model": "admin.logentry", "fields": {"action_flag": 1, "action_time": "2012-04-17 06:40:04", "object_repr": "Category: Category - Sea", "object_id": "2", "change_message": "", "user": 1, "content_type": 11}}, {"pk": 12, "model": "admin.logentry", "fields": {"action_flag": 1, "action_time": "2012-04-15 15:03:59", "object_repr": "background video 1", "object_id": "1", "change_message": "", "user": 1, "content_type": 13}}, {"pk": 11, "model": "admin.logentry", "fields": {"action_flag": 1, "action_time": "2012-04-15 14:47:39", "object_repr": "Story One", "object_id": "1", "change_message": "", "user": 1, "content_type": 26}}, {"pk": 10, "model": "admin.logentry", "fields": {"action_flag": 1, "action_time": "2012-04-15 14:47:35", "object_repr": "Posterframe Test", "object_id": "1", "change_message": "", "user": 1, "content_type": 17}}, {"pk": 9, "model": "admin.logentry", "fields": {"action_flag": 1, "action_time": "2012-04-15 14:47:18", "object_repr": "Jugball Video", "object_id": "2", "change_message": "", "user": 1, "content_type": 16}}, {"pk": 8, "model": "admin.logentry", "fields": {"action_flag": 2, "action_time": "2012-04-12 21:55:19", "object_repr": "Infographic 1", "object_id": "1", "change_message": "Changed infographic_files for infographic_ translation \"Infographic_Translation object\".", "user": 1, "content_type": 22}}, {"pk": 7, "model": "admin.logentry", "fields": {"action_flag": 2, "action_time": "2012-04-12 21:48:18", "object_repr": "Infographic 1", "object_id": "1", "change_message": "Changed infographic_files for infographic_ translation \"Infographic_Translation object\".", "user": 1, "content_type": 22}}, {"pk": 6, "model": "admin.logentry", "fields": {"action_flag": 1, "action_time": "2012-04-03 23:11:03", "object_repr": "about page", "object_id": "1", "change_message": "", "user": 1, "content_type": 31}}, {"pk": 5, "model": "admin.logentry", "fields": {"action_flag": 1, "action_time": "2012-04-03 23:10:51", "object_repr": "Infographic 1", "object_id": "1", "change_message": "", "user": 1, "content_type": 24}}, {"pk": 4, "model": "admin.logentry", "fields": {"action_flag": 1, "action_time": "2012-04-03 23:10:46", "object_repr": "Infographic 1", "object_id": "1", "change_message": "", "user": 1, "content_type": 22}}, {"pk": 3, "model": "admin.logentry", "fields": {"action_flag": 1, "action_time": "2012-04-03 23:09:07", "object_repr": "Featured video", "object_id": "1", "change_message": "", "user": 1, "content_type": 16}}, {"pk": 2, "model": "admin.logentry", "fields": {"action_flag": 1, "action_time": "2012-04-03 23:08:53", "object_repr": "Category: Category1", "object_id": "1", "change_message": "", "user": 1, "content_type": 11}}, {"pk": 1, "model": "admin.logentry", "fields": {"action_flag": 1, "action_time": "2012-04-03 23:07:57", "object_repr": "livinggalapagos.org", "object_id": "1", "change_message": "", "user": 1, "content_type": 9}}, {"pk": 1, "model": "story_database.site", "fields": {"domain": "livinggalapagos.org"}}, {"pk": 1, "model": "story_database.category", "fields": {"name": "Category1", "slug": "category1"}}, {"pk": 2, "model": "story_database.category", "fields": {"name": "Category - Sea", "slug": "category-sea"}}, {"pk": 1, "model": "story_database.category_translation", "fields": {"translation": "Hungry hippo", "parent": 1, "language_code": "en"}}, {"pk": 2, "model": "story_database.category_translation", "fields": {"translation": "Sea", "parent": 2, "language_code": "en"}}, {"pk": 3, "model": "story_database.category_translation", "fields": {"translation": "Mar", "parent": 2, "language_code": "es"}}, {"pk": 1, "model": "story_database.background_video", "fields": {"category": 2, "h264_background": "uploads/background-ideo/h264/backgrounds.m4v", "name": "background video 1", "ogg_background": "uploads/background-video/ogg/backgrounds.ogv", "jpg_background": "uploads/background-video/jpg/jugball-video-thumb.jpg", "slug": "background-video-1"}}, {"pk": 1, "model": "story_database.video", "fields": {"category": 1, "vimeo_id": 84884574, "name": "Featured video", "title": "", "related_content_thumbnail": "", "longitude": null, "creation_date": "2012-04-03", "thumbnail": "", "last_modified": "2012-04-03", "latitude": null, "slug": "featured-video", "tags": [], "description": ""}}, {"pk": 2, "model": "story_database.video", "fields": {"category": 1, "vimeo_id": 21762736, "name": "Jugball Video", "title": "Juggball video", "related_content_thumbnail": "uploads/video/related_thumbs/2012/04/15/jugball-video-thumb.jpg", "longitude": null, "creation_date": "2012-04-15", "thumbnail": "uploads/video/thumbnails/2012/04/15/jugball-video-thumb.jpg", "last_modified": "2012-04-15", "latitude": null, "slug": "jugball-video", "tags": [], "description": "Jugball video description"}}, {"pk": 1, "model": "story_database.poster_frame", "fields": {"poster_frame": "uploads/posterframes/jugball-video-poster.jpg", "name": "Posterframe Test", "slug": "posterframe-test"}}, {"pk": 1, "model": "story_database.infographic", "fields": {"category": null, "name": "Infographic 1", "tag": [], "longitude": null, "creation_date": "2012-04-03", "last_modified": "2012-04-12", "latitude": null, "slug": "infographic-1"}}, {"pk": 1, "model": "story_database.infographic_translation", "fields": {"infographic_files": "uploads/infographics/english-title/twinkies.html", "description": "", "parent": 1, "title": "English Title", "is_interactive": false, "thumbnail": "uploads/infographics/thumbnails/english-title/add alt.png", "language_code": "en", "short_description": "", "slug": "english-title"}}, {"pk": 1, "model": "story_database.related_content", "fields": {"category": null, "name": "Infographic 1", "tag": [], "creation_date": "2012-04-03", "last_modified": "2012-04-03", "slug": "infographic-1"}}, {"pk": 1, "model": "story_database.related_content_translation", "fields": {"photo_galleries": [], "infographics": [1], "videos": [], "parent": 1, "language_code": "en"}}, {"pk": 1, "model": "story_database.story", "fields": {"category": 2, "name": "Story One", "tags": [], "site": 1, "longitude": null, "creation_date": "2012-04-15", "last_modified": "2012-04-17", "latitude": null, "slug": "story-one"}}, {"pk": 2, "model": "story_database.story", "fields": {"category": 2, "name": "Story Two", "tags": [], "site": 1, "longitude": null, "creation_date": "2012-04-17", "last_modified": "2012-04-17", "latitude": null, "slug": "story-two"}}, {"pk": 1, "model": "story_database.story_translation", "fields": {"poster_frame": 1, "description": "An english description", "parent": 1, "headline": "English Headline", "quote": "Some cool English Quote", "single_line_description": "A single line description", "subheadline": "English Subheadline", "featured_video": 2, "language_code": "en", "related_content": null, "quote_attribution": "Donald Desloge"}}, {"pk": 2, "model": "story_database.story_translation", "fields": {"poster_frame": 1, "description": "Long description", "parent": 2, "headline": "Story Two Headline", "quote": "Some quote from some cool guy", "single_line_description": "description", "subheadline": "story subheadline", "featured_video": 1, "language_code": "en", "related_content": null, "quote_attribution": "an attribution"}}, {"pk": 1, "model": "story_database.about_page", "fields": {"slug": "about-page", "last_modified": "2012-04-03", "site": 1, "name": "about page", "creation_date": "2012-04-03"}}, {"pk": 1, "model": "story_database.about_page_translation", "fields": {"about_text": "English about text", "parent": 1, "headline": "Headline", "quote": "quote", "subheadline": "Subheadline test story", "featured_video": 1, "language_code": "en", "related_content": 1, "quote_attribution": "quote"}}, {"pk": 22, "model": "auth.permission", "fields": {"codename": "add_logentry", "name": "Can add log entry", "content_type": 8}}, {"pk": 23, "model": "auth.permission", "fields": {"codename": "change_logentry", "name": "Can change log entry", "content_type": 8}}, {"pk": 24, "model": "auth.permission", "fields": {"codename": "delete_logentry", "name": "Can delete log entry", "content_type": 8}}, {"pk": 4, "model": "auth.permission", "fields": {"codename": "add_group", "name": "Can add group", "content_type": 2}}, {"pk": 5, "model": "auth.permission", "fields": {"codename": "change_group", "name": "Can change group", "content_type": 2}}, {"pk": 6, "model": "auth.permission", "fields": {"codename": "delete_group", "name": "Can delete group", "content_type": 2}}, {"pk": 10, "model": "auth.permission", "fields": {"codename": "add_message", "name": "Can add message", "content_type": 4}}, {"pk": 11, "model": "auth.permission", "fields": {"codename": "change_message", "name": "Can change message", "content_type": 4}}, {"pk": 12, "model": "auth.permission", "fields": {"codename": "delete_message", "name": "Can delete message", "content_type": 4}}, {"pk": 1, "model": "auth.permission", "fields": {"codename": "add_permission", "name": "Can add permission", "content_type": 1}}, {"pk": 2, "model": "auth.permission", "fields": {"codename": "change_permission", "name": "Can change permission", "content_type": 1}}, {"pk": 3, "model": "auth.permission", "fields": {"codename": "delete_permission", "name": "Can delete permission", "content_type": 1}}, {"pk": 7, "model": "auth.permission", "fields": {"codename": "add_user", "name": "Can add user", "content_type": 3}}, {"pk": 8, "model": "auth.permission", "fields": {"codename": "change_user", "name": "Can change user", "content_type": 3}}, {"pk": 9, "model": "auth.permission", "fields": {"codename": "delete_user", "name": "Can delete user", "content_type": 3}}, {"pk": 13, "model": "auth.permission", "fields": {"codename": "add_contenttype", "name": "Can add content type", "content_type": 5}}, {"pk": 14, "model": "auth.permission", "fields": {"codename": "change_contenttype", "name": "Can change content type", "content_type": 5}}, {"pk": 15, "model": "auth.permission", "fields": {"codename": "delete_contenttype", "name": "Can delete content type", "content_type": 5}}, {"pk": 16, "model": "auth.permission", "fields": {"codename": "add_session", "name": "Can add session", "content_type": 6}}, {"pk": 17, "model": "auth.permission", "fields": {"codename": "change_session", "name": "Can change session", "content_type": 6}}, {"pk": 18, "model": "auth.permission", "fields": {"codename": "delete_session", "name": "Can delete session", "content_type": 6}}, {"pk": 19, "model": "auth.permission", "fields": {"codename": "add_site", "name": "Can add site", "content_type": 7}}, {"pk": 20, "model": "auth.permission", "fields": {"codename": "change_site", "name": "Can change site", "content_type": 7}}, {"pk": 21, "model": "auth.permission", "fields": {"codename": "delete_site", "name": "Can delete site", "content_type": 7}}, {"pk": 91, "model": "auth.permission", "fields": {"codename": "add_about_page", "name": "Can add about_ page", "content_type": 31}}, {"pk": 92, "model": "auth.permission", "fields": {"codename": "change_about_page", "name": "Can change about_ page", "content_type": 31}}, {"pk": 93, "model": "auth.permission", "fields": {"codename": "delete_about_page", "name": "Can delete about_ page", "content_type": 31}}, {"pk": 94, "model": "auth.permission", "fields": {"codename": "add_about_page_translation", "name": "Can add about_ page_ translation", "content_type": 32}}, {"pk": 95, "model": "auth.permission", "fields": {"codename": "change_about_page_translation", "name": "Can change about_ page_ translation", "content_type": 32}}, {"pk": 96, "model": "auth.permission", "fields": {"codename": "delete_about_page_translation", "name": "Can delete about_ page_ translation", "content_type": 32}}, {"pk": 37, "model": "auth.permission", "fields": {"codename": "add_background_video", "name": "Can add Background Video", "content_type": 13}}, {"pk": 38, "model": "auth.permission", "fields": {"codename": "change_background_video", "name": "Can change Background Video", "content_type": 13}}, {"pk": 39, "model": "auth.permission", "fields": {"codename": "delete_background_video", "name": "Can delete Background Video", "content_type": 13}}, {"pk": 31, "model": "auth.permission", "fields": {"codename": "add_category", "name": "Can add Category", "content_type": 11}}, {"pk": 32, "model": "auth.permission", "fields": {"codename": "change_category", "name": "Can change Category", "content_type": 11}}, {"pk": 33, "model": "auth.permission", "fields": {"codename": "delete_category", "name": "Can delete Category", "content_type": 11}}, {"pk": 34, "model": "auth.permission", "fields": {"codename": "add_category_translation", "name": "Can add category_ translation", "content_type": 12}}, {"pk": 35, "model": "auth.permission", "fields": {"codename": "change_category_translation", "name": "Can change category_ translation", "content_type": 12}}, {"pk": 36, "model": "auth.permission", "fields": {"codename": "delete_category_translation", "name": "Can delete category_ translation", "content_type": 12}}, {"pk": 88, "model": "auth.permission", "fields": {"codename": "add_featured_story", "name": "Can add Featured Story", "content_type": 30}}, {"pk": 89, "model": "auth.permission", "fields": {"codename": "change_featured_story", "name": "Can change Featured Story", "content_type": 30}}, {"pk": 90, "model": "auth.permission", "fields": {"codename": "delete_featured_story", "name": "Can delete Featured Story", "content_type": 30}}, {"pk": 64, "model": "auth.permission", "fields": {"codename": "add_infographic", "name": "Can add Infographic", "content_type": 22}}, {"pk": 65, "model": "auth.permission", "fields": {"codename": "change_infographic", "name": "Can change Infographic", "content_type": 22}}, {"pk": 66, "model": "auth.permission", "fields": {"codename": "delete_infographic", "name": "Can delete Infographic", "content_type": 22}}, {"pk": 67, "model": "auth.permission", "fields": {"codename": "add_infographic_translation", "name": "Can add infographic_ translation", "content_type": 23}}, {"pk": 68, "model": "auth.permission", "fields": {"codename": "change_infographic_translation", "name": "Can change infographic_ translation", "content_type": 23}}, {"pk": 69, "model": "auth.permission", "fields": {"codename": "delete_infographic_translation", "name": "Can delete infographic_ translation", "content_type": 23}}, {"pk": 52, "model": "auth.permission", "fields": {"codename": "add_photo", "name": "Can add photo", "content_type": 18}}, {"pk": 53, "model": "auth.permission", "fields": {"codename": "change_photo", "name": "Can change photo", "content_type": 18}}, {"pk": 54, "model": "auth.permission", "fields": {"codename": "delete_photo", "name": "Can delete photo", "content_type": 18}}, {"pk": 58, "model": "auth.permission", "fields": {"codename": "add_photo_gallery", "name": "Can add Photo Gallery", "content_type": 20}}, {"pk": 59, "model": "auth.permission", "fields": {"codename": "change_photo_gallery", "name": "Can change Photo Gallery", "content_type": 20}}, {"pk": 60, "model": "auth.permission", "fields": {"codename": "delete_photo_gallery", "name": "Can delete Photo Gallery", "content_type": 20}}, {"pk": 61, "model": "auth.permission", "fields": {"codename": "add_photo_gallery_translation", "name": "Can add photo_ gallery_ translation", "content_type": 21}}, {"pk": 62, "model": "auth.permission", "fields": {"codename": "change_photo_gallery_translation", "name": "Can change photo_ gallery_ translation", "content_type": 21}}, {"pk": 63, "model": "auth.permission", "fields": {"codename": "delete_photo_gallery_translation", "name": "Can delete photo_ gallery_ translation", "content_type": 21}}, {"pk": 55, "model": "auth.permission", "fields": {"codename": "add_photo_translation", "name": "Can add photo_ translation", "content_type": 19}}, {"pk": 56, "model": "auth.permission", "fields": {"codename": "change_photo_translation", "name": "Can change photo_ translation", "content_type": 19}}, {"pk": 57, "model": "auth.permission", "fields": {"codename": "delete_photo_translation", "name": "Can delete photo_ translation", "content_type": 19}}, {"pk": 49, "model": "auth.permission", "fields": {"codename": "add_poster_frame", "name": "Can add Poster Frame", "content_type": 17}}, {"pk": 50, "model": "auth.permission", "fields": {"codename": "change_poster_frame", "name": "Can change Poster Frame", "content_type": 17}}, {"pk": 51, "model": "auth.permission", "fields": {"codename": "delete_poster_frame", "name": "Can delete Poster Frame", "content_type": 17}}, {"pk": 70, "model": "auth.permission", "fields": {"codename": "add_related_content", "name": "Can add Related Content", "content_type": 24}}, {"pk": 71, "model": "auth.permission", "fields": {"codename": "change_related_content", "name": "Can change Related Content", "content_type": 24}}, {"pk": 72, "model": "auth.permission", "fields": {"codename": "delete_related_content", "name": "Can delete Related Content", "content_type": 24}}, {"pk": 73, "model": "auth.permission", "fields": {"codename": "add_related_content_translation", "name": "Can add related_ content_ translation", "content_type": 25}}, {"pk": 74, "model": "auth.permission", "fields": {"codename": "change_related_content_translation", "name": "Can change related_ content_ translation", "content_type": 25}}, {"pk": 75, "model": "auth.permission", "fields": {"codename": "delete_related_content_translation", "name": "Can delete related_ content_ translation", "content_type": 25}}, {"pk": 82, "model": "auth.permission", "fields": {"codename": "add_research", "name": "Can add research", "content_type": 28}}, {"pk": 83, "model": "auth.permission", "fields": {"codename": "change_research", "name": "Can change research", "content_type": 28}}, {"pk": 84, "model": "auth.permission", "fields": {"codename": "delete_research", "name": "Can delete research", "content_type": 28}}, {"pk": 85, "model": "auth.permission", "fields": {"codename": "add_research_translation", "name": "Can add research_ translation", "content_type": 29}}, {"pk": 86, "model": "auth.permission", "fields": {"codename": "change_research_translation", "name": "Can change research_ translation", "content_type": 29}}, {"pk": 87, "model": "auth.permission", "fields": {"codename": "delete_research_translation", "name": "Can delete research_ translation", "content_type": 29}}, {"pk": 28, "model": "auth.permission", "fields": {"codename": "add_resources", "name": "Can add Resource", "content_type": 10}}, {"pk": 29, "model": "auth.permission", "fields": {"codename": "change_resources", "name": "Can change Resource", "content_type": 10}}, {"pk": 30, "model": "auth.permission", "fields": {"codename": "delete_resources", "name": "Can delete Resource", "content_type": 10}}, {"pk": 25, "model": "auth.permission", "fields": {"codename": "add_site", "name": "Can add site", "content_type": 9}}, {"pk": 26, "model": "auth.permission", "fields": {"codename": "change_site", "name": "Can change site", "content_type": 9}}, {"pk": 27, "model": "auth.permission", "fields": {"codename": "delete_site", "name": "Can delete site", "content_type": 9}}, {"pk": 76, "model": "auth.permission", "fields": {"codename": "add_story", "name": "Can add story", "content_type": 26}}, {"pk": 77, "model": "auth.permission", "fields": {"codename": "change_story", "name": "Can change story", "content_type": 26}}, {"pk": 78, "model": "auth.permission", "fields": {"codename": "delete_story", "name": "Can delete story", "content_type": 26}}, {"pk": 79, "model": "auth.permission", "fields": {"codename": "add_story_translation", "name": "Can add story_ translation", "content_type": 27}}, {"pk": 80, "model": "auth.permission", "fields": {"codename": "change_story_translation", "name": "Can change story_ translation", "content_type": 27}}, {"pk": 81, "model": "auth.permission", "fields": {"codename": "delete_story_translation", "name": "Can delete story_ translation", "content_type": 27}}, {"pk": 40, "model": "auth.permission", "fields": {"codename": "add_tag", "name": "Can add tag", "content_type": 14}}, {"pk": 41, "model": "auth.permission", "fields": {"codename": "change_tag", "name": "Can change tag", "content_type": 14}}, {"pk": 42, "model": "auth.permission", "fields": {"codename": "delete_tag", "name": "Can delete tag", "content_type": 14}}, {"pk": 43, "model": "auth.permission", "fields": {"codename": "add_tag_translation", "name": "Can add tag_ translation", "content_type": 15}}, {"pk": 44, "model": "auth.permission", "fields": {"codename": "change_tag_translation", "name": "Can change tag_ translation", "content_type": 15}}, {"pk": 45, "model": "auth.permission", "fields": {"codename": "delete_tag_translation", "name": "Can delete tag_ translation", "content_type": 15}}, {"pk": 46, "model": "auth.permission", "fields": {"codename": "add_video", "name": "Can add video", "content_type": 16}}, {"pk": 47, "model": "auth.permission", "fields": {"codename": "change_video", "name": "Can change video", "content_type": 16}}, {"pk": 48, "model": "auth.permission", "fields": {"codename": "delete_video", "name": "Can delete video", "content_type": 16}}, {"pk": 1, "model": "auth.user", "fields": {"username": "thedesloge", "first_name": "", "last_name": "", "is_active": true, "is_superuser": true, "is_staff": true, "last_login": "2012-04-03 23:07:34", "groups": [], "user_permissions": [], "password": "sha1$c81ce$10bedcca192812446014c710684db3d3027fbc3e", "email": "me@me.com", "date_joined": "2012-04-03 23:02:42"}}]